multimodal_timesfm/__init__.py
multimodal_timesfm/arima_baseline.py
multimodal_timesfm/baseline_trainer.py
multimodal_timesfm/cross_validation.py
multimodal_timesfm/evaluation.py
multimodal_timesfm/multimodal_dataset.py
multimodal_timesfm/multimodal_fusion.py
multimodal_timesfm/multimodal_patched_decoder.py
multimodal_timesfm/multimodal_timesfm.py
multimodal_timesfm/preprocessing.py
multimodal_timesfm/py.typed
multimodal_timesfm/text_encoder.py
multimodal_timesfm/trainer.py
multimodal_timesfm/utils/__init__.py
multimodal_timesfm/utils/collate.py
multimodal_timesfm/utils/device.py
multimodal_timesfm/utils/logging.py
multimodal_timesfm/utils/model.py
multimodal_timesfm/utils/seed.py
multimodal_timesfm/utils/yaml.py
multimodal_timesfm-0.1.4.dist-info/METADATA
multimodal_timesfm-0.1.4.dist-info/WHEEL
multimodal_timesfm-0.1.4.dist-info/licenses/LICENSE
multimodal_timesfm-0.1.4.dist-info/RECORD
