Metadata-Version: 2.4
Name: multimodal-timesfm
Version: 0.1.4
Summary: Multimodal extension of Google's TimesFM for time series forecasting with text
Project-URL: Homepage, https://github.com/himura467/multimodal-timesfm
Project-URL: Documentation, https://github.com/himura467/multimodal-timesfm
Project-URL: Repository, https://github.com/himura467/multimodal-timesfm
Project-URL: Bug Tracker, https://github.com/himura467/multimodal-timesfm/issues
Author-email: Akito Shitara <mitarashidango0927@gmail.com>
License: MIT License
License-File: LICENSE
Classifier: Operating System :: OS Independent
Classifier: Programming Language :: Python :: 3
Classifier: Topic :: Scientific/Engineering :: Artificial Intelligence
Requires-Python: >=3.11
Requires-Dist: sentence-transformers>=5.1.0
Requires-Dist: sentencepiece>=0.2.1
Requires-Dist: timesfm[torch]>=1.3.0
Requires-Dist: torch>=2.8.0
Provides-Extra: all
Requires-Dist: matplotlib>=3.10.7; extra == 'all'
Requires-Dist: statsmodels>=0.14.5; extra == 'all'
Provides-Extra: experiment
Requires-Dist: statsmodels>=0.14.5; extra == 'experiment'
Provides-Extra: plot
Requires-Dist: matplotlib>=3.10.7; extra == 'plot'
